core/__init__.py
core/utils.py
deepkime-0.0.0.dist-info/LICENSE
deepkime-0.0.0.dist-info/METADATA
deepkime-0.0.0.dist-info/WHEEL
deepkime-0.0.0.dist-info/top_level.txt
deepkime-0.0.0.dist-info/RECORD
